robespierre/__init__.py
robespierre/__main__.py
robespierre/_version.py
robespierre/models.py
robespierre/runner.py
robespierre/utils/__init__.py
robespierre/utils/files.py
robespierre/utils/mail.py
robespierre/vendor/a
robespierre/vendor/scorch
robespierre-0.1.1.dist-info/LICENSE
robespierre-0.1.1.dist-info/METADATA
robespierre-0.1.1.dist-info/WHEEL
robespierre-0.1.1.dist-info/entry_points.txt
robespierre-0.1.1.dist-info/top_level.txt
robespierre-0.1.1.dist-info/RECORD
