Metadata-Version: 2.1
Name: robespierre
Version: 0.1.1
Summary: Wrapper for scorch to send report as email
Home-page: https://gitlab.com/daufinsyd/robespierre
Author: Sydney Gems
Author-email: sydney@gems.technology
Project-URL: Bug Tracker, https://gitlab.com/daufinsyd/robespierre/-/issues
Classifier: Development Status :: 3 - Alpha
Classifier: Programming Language :: Python :: 3
Classifier: License :: OSI Approved :: GNU Affero General Public License v3 or later (AGPLv3+)
Classifier: Operating System :: POSIX :: Linux
Classifier: Topic :: System
Requires-Python: >=3.6
License-File: LICENSE
Requires-Dist: coloredlogs
Requires-Dist: click
Requires-Dist: tomli
